<?xml version="1.0" encoding="utf-8"?>
<data>
  <DataType Name="Data Types2" BaseType="" ArrayType="" Length="" InitialValue="" EnumValue="" Comment="" OffsetChannel="" OffsetBit="" IsControllerDefinedType="false" Order="0" OffsetType="">
    <DataType Name="sSMSControl" BaseType="STRUCT" ArrayType="" Length="" InitialValue="" EnumValue="" Comment="" OffsetChannel="" OffsetBit="" IsControllerDefinedType="false" Order="96" OffsetType="NJ">
      <DataType Name="Alarm" BaseType="BOOL" ArrayType="" Length="" InitialValue="" EnumValue="" Comment="" OffsetChannel="" OffsetBit="" IsControllerDefinedType="false" Order="0" OffsetType="" />
      <DataType Name="Block" BaseType="BOOL" ArrayType="" Length="" InitialValue="" EnumValue="" Comment="" OffsetChannel="" OffsetBit="" IsControllerDefinedType="false" Order="0" OffsetType="" />
    </DataType>
    <DataType Name="sSMSStaticData" BaseType="STRUCT" ArrayType="" Length="" InitialValue="" EnumValue="" Comment="" OffsetChannel="" OffsetBit="" IsControllerDefinedType="false" Order="95" OffsetType="NJ">
      <DataType Name="Number" BaseType="UINT" ArrayType="" Length="" InitialValue="" EnumValue="" Comment="" OffsetChannel="" OffsetBit="" IsControllerDefinedType="false" Order="0" OffsetType="" />
      <DataType Name="Message" BaseType="STRING[155]" ArrayType="" Length="" InitialValue="" EnumValue="" Comment="" OffsetChannel="" OffsetBit="" IsControllerDefinedType="false" Order="0" OffsetType="" />
      <DataType Name="Receiver" BaseType="ARRAY[1..19] OF UINT" ArrayType="" Length="" InitialValue="" EnumValue="" Comment="" OffsetChannel="" OffsetBit="" IsControllerDefinedType="false" Order="0" OffsetType="" />
      <DataType Name="Delay_SV" BaseType="UINT" ArrayType="" Length="" InitialValue="" EnumValue="" Comment="" OffsetChannel="" OffsetBit="" IsControllerDefinedType="false" Order="0" OffsetType="" />
      <DataType Name="Phone" BaseType="ARRAY[0..19] OF STRING[11]" ArrayType="" Length="" InitialValue="" EnumValue="" Comment="" OffsetChannel="" OffsetBit="" IsControllerDefinedType="false" Order="0" OffsetType="" />
    </DataType>
    <DataType Name="sSMSDynamicData" BaseType="STRUCT" ArrayType="" Length="" InitialValue="" EnumValue="" Comment="" OffsetChannel="" OffsetBit="" IsControllerDefinedType="false" Order="94" OffsetType="NJ">
      <DataType Name="Number" BaseType="UINT" ArrayType="" Length="" InitialValue="" EnumValue="" Comment="" OffsetChannel="" OffsetBit="" IsControllerDefinedType="false" Order="0" OffsetType="" />
      <DataType Name="ReceiverStack" BaseType="ARRAY[1..19] OF UINT" ArrayType="" Length="" InitialValue="" EnumValue="" Comment="" OffsetChannel="" OffsetBit="" IsControllerDefinedType="false" Order="0" OffsetType="" />
      <DataType Name="Delay_PV" BaseType="UINT" ArrayType="" Length="" InitialValue="" EnumValue="" Comment="" OffsetChannel="" OffsetBit="" IsControllerDefinedType="false" Order="0" OffsetType="" />
      <DataType Name="NextReceiver" BaseType="UINT" ArrayType="" Length="" InitialValue="" EnumValue="" Comment="" OffsetChannel="" OffsetBit="" IsControllerDefinedType="false" Order="0" OffsetType="" />
      <DataType Name="Ack_Received" BaseType="BOOL" ArrayType="" Length="" InitialValue="" EnumValue="" Comment="" OffsetChannel="" OffsetBit="" IsControllerDefinedType="false" Order="0" OffsetType="" />
      <DataType Name="Ack_Send" BaseType="BOOL" ArrayType="" Length="" InitialValue="" EnumValue="" Comment="" OffsetChannel="" OffsetBit="" IsControllerDefinedType="false" Order="0" OffsetType="" />
      <DataType Name="Ack_Receiver" BaseType="UINT" ArrayType="" Length="" InitialValue="" EnumValue="" Comment="" OffsetChannel="" OffsetBit="" IsControllerDefinedType="false" Order="0" OffsetType="" />
    </DataType>
    <DataType Name="sATCommands" BaseType="STRUCT" ArrayType="" Length="" InitialValue="" EnumValue="" Comment="" OffsetChannel="" OffsetBit="" IsControllerDefinedType="false" Order="93" OffsetType="NJ">
      <DataType Name="ReadSMS" BaseType="STRING[10]" ArrayType="" Length="" InitialValue="" EnumValue="" Comment="" OffsetChannel="" OffsetBit="" IsControllerDefinedType="false" Order="0" OffsetType="" />
      <DataType Name="SendSMS" BaseType="STRING[10]" ArrayType="" Length="" InitialValue="" EnumValue="" Comment="" OffsetChannel="" OffsetBit="" IsControllerDefinedType="false" Order="0" OffsetType="" />
      <DataType Name="SignalLevel" BaseType="STRING[10]" ArrayType="" Length="" InitialValue="" EnumValue="" Comment="" OffsetChannel="" OffsetBit="" IsControllerDefinedType="false" Order="0" OffsetType="" />
      <DataType Name="DeleteSMS" BaseType="STRING[10]" ArrayType="" Length="" InitialValue="" EnumValue="" Comment="" OffsetChannel="" OffsetBit="" IsControllerDefinedType="false" Order="0" OffsetType="" />
      <DataType Name="Dial" BaseType="STRING[4]" ArrayType="" Length="" InitialValue="" EnumValue="" Comment="" OffsetChannel="" OffsetBit="" IsControllerDefinedType="false" Order="0" OffsetType="" />
      <DataType Name="DialEnd" BaseType="STRING[4]" ArrayType="" Length="" InitialValue="" EnumValue="" Comment="" OffsetChannel="" OffsetBit="" IsControllerDefinedType="false" Order="0" OffsetType="" />
    </DataType>
    <DataType Name="eSteps" BaseType="ENUM" ArrayType="" Length="" InitialValue="" EnumValue="" Comment="" OffsetChannel="" OffsetBit="" IsControllerDefinedType="false" Order="0" OffsetType="">
      <DataType Name="CheckSMS" BaseType="DINT" ArrayType="" Length="" InitialValue="" EnumValue="1" Comment="" OffsetChannel="" OffsetBit="" IsControllerDefinedType="false" Order="0" OffsetType="" />
      <DataType Name="ReceiveSMS" BaseType="DINT" ArrayType="" Length="" InitialValue="" EnumValue="2" Comment="" OffsetChannel="" OffsetBit="" IsControllerDefinedType="false" Order="0" OffsetType="" />
      <DataType Name="SendPhoneSMS" BaseType="DINT" ArrayType="" Length="" InitialValue="" EnumValue="3" Comment="" OffsetChannel="" OffsetBit="" IsControllerDefinedType="false" Order="0" OffsetType="" />
      <DataType Name="ReceivePhoneSMSAck" BaseType="DINT" ArrayType="" Length="" InitialValue="" EnumValue="4" Comment="" OffsetChannel="" OffsetBit="" IsControllerDefinedType="false" Order="0" OffsetType="" />
      <DataType Name="SendMessageSMS" BaseType="DINT" ArrayType="" Length="" InitialValue="" EnumValue="5" Comment="" OffsetChannel="" OffsetBit="" IsControllerDefinedType="false" Order="0" OffsetType="" />
      <DataType Name="DeleteSMS" BaseType="DINT" ArrayType="" Length="" InitialValue="" EnumValue="6" Comment="" OffsetChannel="" OffsetBit="" IsControllerDefinedType="false" Order="0" OffsetType="" />
      <DataType Name="CallPhone" BaseType="DINT" ArrayType="" Length="" InitialValue="" EnumValue="7" Comment="" OffsetChannel="" OffsetBit="" IsControllerDefinedType="false" Order="0" OffsetType="" />
      <DataType Name="ReadSignalLevel" BaseType="DINT" ArrayType="" Length="" InitialValue="" EnumValue="8" Comment="" OffsetChannel="" OffsetBit="" IsControllerDefinedType="false" Order="0" OffsetType="" />
      <DataType Name="ReceiveSignalLevel" BaseType="DINT" ArrayType="" Length="" InitialValue="" EnumValue="9" Comment="" OffsetChannel="" OffsetBit="" IsControllerDefinedType="false" Order="0" OffsetType="" />
    </DataType>
  </DataType>
</data>